

{
    "sEmptyTable": "Nenhum registro encontrado",
    "sInfo": "Mostrando _START_ - _END_ de _TOTAL_",
    "sInfoEmpty": "Nenhum registro encontrado",
    "sInfoFiltered": "(Filtrados de _MAX_ registros)",
    "sInfoPostFix": "",
    "sInfoThousands": ".",
    "sLengthMenu": "_MENU_ ",
    "sLoadingRecords": "Carregando...",
    "sProcessing": "Processando...",
    "sZeroRecords": "Nenhum registro encontrado",
    "sSearch": "Pesquisar",
    "oPaginate": {
        "sNext": "Próximo",
        "sPrevious": "Anterior",
        "sFirst": "Primeiro",
        "sLast": "Último"
    },
    "oAria": {
        "sSortAscending": ": Ordenar colunas de forma ascendente",
        "sSortDescending": ": Ordenar colunas de forma descendente"
    }
}
